Metadata-Version: 1.0
Name: wodarhospur-core
Version: 0.1
Summary: The core package of the Lore Keeper
Home-page: http://github.com/dataloudlabs
Author: Pedro Sousa
Author-email: pedro@pjsousa.com
License: MIT
Platform: UNKNOWN
